jpreprocess-0.1.4.dist-info/METADATA
jpreprocess-0.1.4.dist-info/WHEEL
jpreprocess/dictionary.py
jpreprocess/jpreprocess.pyi
jpreprocess/py.typed
jpreprocess/__init__.py
jpreprocess/jpreprocess.cp310-win32.pyd
jpreprocess-0.1.4.dist-info/RECORD
