Metadata-Version: 2.3
Name: jpreprocess
Version: 0.1.4
Classifier: Programming Language :: Rust
Classifier: Programming Language :: Python :: Implementation :: CPython
Classifier: Programming Language :: Python :: Implementation :: PyPy
Classifier: License :: OSI Approved :: BSD License
Classifier: Topic :: Scientific/Engineering
Classifier: Topic :: Software Development
Classifier: Intended Audience :: Science/Research
Classifier: Intended Audience :: Developers
Requires-Dist: importlib-resources ; python_version < '3.9'
Requires-Dist: tqdm ; extra == 'progress'
Requires-Dist: pytest >=8.0.1 ; extra == 'dev'
Provides-Extra: progress
Provides-Extra: dev
Summary: Japanese text preprocessor for Text-to-Speech application (OpenJTalk rewrite in rust language).
Keywords: tts,openjtalk,library
License: BSD-3-Clause
Requires-Python: >=3.8, <=3.12
Project-URL: Source Code, https://github.com/jpreprocess/jpreprocess
